gds2openEMS/__init__.py
gds2openEMS/util_gds_reader.py
gds2openEMS/util_meshlines.py
gds2openEMS/util_simulation_setup.py
gds2openEMS/util_stackup_reader.py
gds2openEMS/util_utilities.py
gds2openems-0.1.3.dist-info/licenses/LICENSE
gds2openems-0.1.3.dist-info/METADATA
gds2openems-0.1.3.dist-info/WHEEL
gds2openems-0.1.3.dist-info/top_level.txt
gds2openems-0.1.3.dist-info/RECORD
