Metadata-Version: 2.4
Name: gds2openEMS
Version: 0.1.3
Summary: Create and run openEMS FDTD model from RFIC GDSII layout file
Author-email: Volker Muehlhaus <volker@muehlhaus.com>
License: Apache
Requires-Python: >=3.6
License-File: LICENSE
Requires-Dist: gdspy>1.6.0
Requires-Dist: CSXCAD
Requires-Dist: openEMS
Requires-Dist: scikit-rf
Dynamic: license-file
